{"cameraMode":{"drawMode":0,"name":"Shaded","section":"Shading Mode"},"sceneLighting":true,"audioPlay":false,"sceneViewState":{"m_AlwaysRefresh":false,"showFog":true,"showSkybox":true,"showFlares":true,"showImageEffects":true,"showParticleSystems":true,"showVisualEffectGraphs":true,"m_FxEnabled":true},"in2DMode":false,"pivot":{"x":287.6510009765625,"y":-35.72052764892578,"z":-94.88905334472656},"rotation":{"x":-0.14347195625305177,"y":-0.7061277031898499,"z":0.14962515234947205,"w":-0.6770700216293335},"size":167.693603515625,"orthographic":false}